SF_Tree_Identifier/Address.py
SF_Tree_Identifier/__init__.py
SF_Tree_Identifier/__main__.py
SF_Tree_Identifier/identify_trees.py
SF_Tree_Identifier/test.py
SF_Tree_Identifier/data/SF_trees.pkl
SF_Tree_Identifier/data/species_dict.pkl
SF_Tree_Identifier/data/street_names.json
SF_Tree_Identifier/data/street_types.json
SF_Tree_Identifier/tests/Address_test.py
SF_Tree_Identifier/tests/tree_identifier_test.py
SF_Tree_Identifier-0.4.1.dist-info/LICENSE
SF_Tree_Identifier-0.4.1.dist-info/METADATA
SF_Tree_Identifier-0.4.1.dist-info/WHEEL
SF_Tree_Identifier-0.4.1.dist-info/top_level.txt
SF_Tree_Identifier-0.4.1.dist-info/RECORD
