Metadata-Version: 2.1
Name: SF-Tree-Identifier
Version: 0.4.1
Summary: Get information about trees at specific addresses in San Francisco
Author-email: Zaven Cook <zavencook@gmail.com>
License: GNU GENERAL PUBLIC LICENSE
Project-URL: Homepage, https://github.com/zcook7904/SF_Tree_Identifier
Project-URL: Bug Tracker, https://github.com/zcook7904/SF_Tree_Identifier/issues
Classifier: Programming Language :: Python :: 3
Classifier: License :: OSI Approved :: MIT License
Classifier: Operating System :: OS Independent
Requires-Python: >=3.7
License-File: LICENSE
Requires-Dist: pandas
Requires-Dist: thefuzz[python-levenshtein]
Requires-Dist: pytest
